{
  "unversionedId": "Modules/Customizable",
  "id": "Modules/Customizable",
  "title": "Customizable",
  "description": "",
  "source": "@site/docs/Modules/Customizable.mdx",
  "sourceDirName": "Modules",
  "slug": "/Modules/Customizable",
  "permalink": "/docs/Modules/Customizable",
  "draft": false,
  "editUrl": "#/docs/Modules/Customizable.mdx",
  "tags": [],
  "version": "current",
  "frontMatter": {},
  "sidebar": "tutorialSidebar",
  "previous": {
    "title": "CRUD",
    "permalink": "/docs/Modules/CRUD"
  },
  "next": {
    "title": "Email Auth Module",
    "permalink": "/docs/Modules/Email Auth Module"
  }
}